polvo_cli/__init__.py
polvo_cli/client.py
polvo_cli/config.py
polvo_cli/formatters.py
polvo_cli/main.py
polvo_cli/models.py
polvo_cli-0.1.0.dist-info/METADATA
polvo_cli-0.1.0.dist-info/WHEEL
polvo_cli-0.1.0.dist-info/entry_points.txt
polvo_cli-0.1.0.dist-info/RECORD
