Metadata-Version: 2.4
Name: polvo-cli
Version: 0.1.0
Summary: CLI for Polvo - Test embedding models on your data
Requires-Python: >=3.8
Requires-Dist: httpx>=0.25.0
Requires-Dist: pydantic>=2.5.0
Requires-Dist: python-dotenv>=1.0.0
Requires-Dist: rich>=13.7.0
Requires-Dist: typer[all]>=0.9.0
Provides-Extra: build
Requires-Dist: build==1.2.2.post1; extra == 'build'
Requires-Dist: bump2version==1.0.1; extra == 'build'
Requires-Dist: setuptools==75.3.2; extra == 'build'
Requires-Dist: twine==6.1.0; extra == 'build'
Requires-Dist: wheel==0.45.1; extra == 'build'
Provides-Extra: dev
Requires-Dist: black>=23.0.0; extra == 'dev'
Requires-Dist: build==1.2.2.post1; extra == 'dev'
Requires-Dist: bump2version==1.0.1; extra == 'dev'
Requires-Dist: pytest>=7.4.0; extra == 'dev'
Requires-Dist: ruff>=0.1.0; extra == 'dev'
Requires-Dist: setuptools==75.3.2; extra == 'dev'
Requires-Dist: twine==6.1.0; extra == 'dev'
Requires-Dist: wheel==0.45.1; extra == 'dev'
